MANIFEST.in
README.md
setup.py
bin/mothermayi
mothermayi/__init__.py
mothermayi/colors.py
mothermayi/config.py
mothermayi/entryway.py
mothermayi/errors.py
mothermayi/files.py
mothermayi/git.py
mothermayi/hook.py
mothermayi/pre_commit.py
mothermayi/process.py
mothermayi.egg-info/PKG-INFO
mothermayi.egg-info/SOURCES.txt
mothermayi.egg-info/dependency_links.txt
mothermayi.egg-info/requires.txt
mothermayi.egg-info/top_level.txt