Metadata-Version: 1.0
Name: mothermayi
Version: 0.4
Summary: A system for installing and managing git commit hooks
Home-page: https://github.com/EliRibble/mothermayi
Author: EliRibble
Author-email: junk@theribbles.org
License: UNKNOWN
Platform: UNKNOWN
